microkan/KANLayer.py
microkan/LBFGS.py
microkan/MLP.py
microkan/MultKAN.py
microkan/__init__.py
microkan/spline.py
microkan/utils.py
microkan-0.1.0.dist-info/licenses/LICENSE
microkan-0.1.0.dist-info/METADATA
microkan-0.1.0.dist-info/WHEEL
microkan-0.1.0.dist-info/top_level.txt
microkan-0.1.0.dist-info/RECORD
