Metadata-Version: 2.4
Name: microkan
Version: 0.1.0
Summary: A Kolmogorov Arnold Network for Edge Devices
Home-page: https://github.com/alirezaafzalaghaei/microkan
Author: Alireza Afzal Aghaei
Author-email: alirezaafzalaghaei@gmail.com
Classifier: Programming Language :: Python :: 3
Classifier: License :: OSI Approved :: MIT License
Classifier: Operating System :: OS Independent
Requires-Python: >=3.6
License-File: LICENSE
Dynamic: author
Dynamic: author-email
Dynamic: classifier
Dynamic: description
Dynamic: description-content-type
Dynamic: home-page
Dynamic: license-file
Dynamic: requires-python
Dynamic: summary
